<?xml version="1.0" encoding="UTF-8" standalone="no"?>
<worldnodes>
    <node>
        <type>ObstacleSignifier</type>
        <name>totem_obstacle</name>
        <uniqueID>452471</uniqueID>
        <xPosition>90.500000</xPosition>
        <yPosition>1001.545410</yPosition>
        <zPosition>100.000000</zPosition>
        <motionType>0</motionType>
        <speedType>0</speedType>
    </node>
    <node>
        <type>ObstacleSignifier</type>
        <name>totem2_obstacle</name>
        <uniqueID>724325</uniqueID>
        <xPosition>90.500000</xPosition>
        <yPosition>93.597008</yPosition>
        <zPosition>100.000000</zPosition>
        <motionType>0</motionType>
        <speedType>0</speedType>
    </node>
    <node>
        <type>ObstacleSignifier</type>
        <name>obstacle1_obstacle</name>
        <uniqueID>659292</uniqueID>
        <xPosition>801.035889</xPosition>
        <yPosition>317.123169</yPosition>
        <zPosition>100.000000</zPosition>
        <motionType>2</motionType>
        <speedType>2</speedType>
    </node>
    <node>
        <type>ObstacleSignifier</type>
        <name>totem2_obstacle</name>
        <uniqueID>650096</uniqueID>
        <xPosition>1004.474609</xPosition>
        <yPosition>537.508118</yPosition>
        <zPosition>100.000000</zPosition>
        <motionType>0</motionType>
        <speedType>0</speedType>
    </node>
</worldnodes>